cameras_dashboard/ResizeObserver.es-dev.js
cameras_dashboard/ResizeObserver.es-dev2.js
cameras_dashboard/__init__.py
cameras_dashboard/action-struct-dev.js
cameras_dashboard/add-all-tz-dev.js
cameras_dashboard/add-camera-dialog-dev.js
cameras_dashboard/add-camera-model-dialog-dev.js
cameras_dashboard/alarm_control_panel-dev.js
cameras_dashboard/auth-dev.js
cameras_dashboard/automation-dev.js
cameras_dashboard/base-card-struct-dev.js
cameras_dashboard/brands-url-dev.js
cameras_dashboard/c.004a7b01.js
cameras_dashboard/c.004a7b01.js.gz
cameras_dashboard/c.006343e2.js
cameras_dashboard/c.006343e2.js.gz
cameras_dashboard/c.068e357b.js
cameras_dashboard/c.068e357b.js.gz
cameras_dashboard/c.0ab5e714.js
cameras_dashboard/c.0ab5e714.js.gz
cameras_dashboard/c.0ab76581.js
cameras_dashboard/c.0ab76581.js.gz
cameras_dashboard/c.0ae90a90.js
cameras_dashboard/c.0ae90a90.js.gz
cameras_dashboard/c.0c5fd32e.js
cameras_dashboard/c.0c5fd32e.js.gz
cameras_dashboard/c.0d0a5b8b.js
cameras_dashboard/c.0d0a5b8b.js.gz
cameras_dashboard/c.0eff5f5b.js
cameras_dashboard/c.0eff5f5b.js.gz
cameras_dashboard/c.1360dbd1.js
cameras_dashboard/c.1360dbd1.js.gz
cameras_dashboard/c.143f8cca.js
cameras_dashboard/c.143f8cca.js.gz
cameras_dashboard/c.144e89ef.js
cameras_dashboard/c.144e89ef.js.gz
cameras_dashboard/c.19cc3208.js
cameras_dashboard/c.19cc3208.js.gz
cameras_dashboard/c.1cd3f1d5.js
cameras_dashboard/c.1cd3f1d5.js.gz
cameras_dashboard/c.1d918317.js
cameras_dashboard/c.1ded644c.js
cameras_dashboard/c.1ea830e2.js
cameras_dashboard/c.1ea830e2.js.gz
cameras_dashboard/c.2036cb65.js
cameras_dashboard/c.2036cb65.js.gz
cameras_dashboard/c.21d03eeb.js
cameras_dashboard/c.21d03eeb.js.gz
cameras_dashboard/c.2465bf13.js
cameras_dashboard/c.2465bf13.js.gz
cameras_dashboard/c.24bd2446.js
cameras_dashboard/c.24bd2446.js.gz
cameras_dashboard/c.25c3182d.js
cameras_dashboard/c.25c3182d.js.gz
cameras_dashboard/c.27000c6b.js
cameras_dashboard/c.27000c6b.js.gz
cameras_dashboard/c.27b7c0a6.js
cameras_dashboard-20221009112053.dist-info/LICENSE
cameras_dashboard-20221009112053.dist-info/METADATA
cameras_dashboard-20221009112053.dist-info/WHEEL
cameras_dashboard-20221009112053.dist-info/top_level.txt
cameras_dashboard-20221009112053.dist-info/RECORD
