Metadata-Version: 2.1
Name: cameras-dashboard
Version: 20221009112053
Summary: The Cameras Dashboard frontend
Home-page: https://github.com/racelandshop/camera-dashboard-frontend
Author: Rogério Ribeiro
Author-email: zroger499@gmail.com
License: UNKNOWN
Platform: UNKNOWN
